Metadata-Version: 2.1
Name: BDevManager
Version: 0.0.16
Summary: A BDM ENG!
Home-page: https://github.com/BlackFoxgamingstudio/andrew_bdm.git
Author: blackfox
Author-email: andrew@blackfoxstudios.org
